<?xml version="1.0" encoding="UTF-8"?>
<!DOCTYPE why3session PUBLIC "-//Why3//proof session v5//EN"
"http://why3.lri.fr/why3session.dtd">
<why3session shape_version="8">
<prover id="0" name="Z3" version="4.8.4" timelimit="1" steplimit="0" memlimit="1000"/>
<prover id="1" name="Alt-Ergo" version="2.0.0" timelimit="5" steplimit="0" memlimit="1000"/>
<prover id="2" name="Alt-Ergo" version="2.3.0" timelimit="5" steplimit="0" memlimit="1000"/>
<prover id="3" name="CVC4" version="1.7" timelimit="1" steplimit="0" memlimit="1000"/>
<file proved="true">
<path name=".."/><path name="selection_sort.mlw"/>
<theory name="SelectionSort" proved="true">
 <goal name="VC selection_sort" expl="VC for selection_sort" proved="true">
 <transf name="split_vc" proved="true" >
  <goal name="VC selection_sort.0" expl="precondition" proved="true">
  <proof prover="3"><result status="valid" time="0.06" steps="12544"/></proof>
  </goal>
  <goal name="VC selection_sort.1" expl="loop invariant init" proved="true">
  <proof prover="3"><result status="valid" time="0.06" steps="13735"/></proof>
  </goal>
  <goal name="VC selection_sort.2" expl="loop invariant init" proved="true">
  <proof prover="3"><result status="valid" time="0.10" steps="21706"/></proof>
  </goal>
  <goal name="VC selection_sort.3" expl="loop invariant init" proved="true">
  <proof prover="3"><result status="valid" time="0.08" steps="14422"/></proof>
  </goal>
  <goal name="VC selection_sort.4" expl="loop invariant init" proved="true">
  <proof prover="3"><result status="valid" time="0.04" steps="12636"/></proof>
  </goal>
  <goal name="VC selection_sort.5" expl="loop invariant init" proved="true">
  <proof prover="3"><result status="valid" time="0.05" steps="15561"/></proof>
  </goal>
  <goal name="VC selection_sort.6" expl="index in array bounds" proved="true">
  <proof prover="3"><result status="valid" time="0.06" steps="20525"/></proof>
  </goal>
  <goal name="VC selection_sort.7" expl="index in array bounds" proved="true">
  <proof prover="3"><result status="valid" time="0.06" steps="20529"/></proof>
  </goal>
  <goal name="VC selection_sort.8" expl="loop invariant preservation" proved="true">
  <proof prover="3"><result status="valid" time="0.04" steps="13116"/></proof>
  </goal>
  <goal name="VC selection_sort.9" expl="loop invariant preservation" proved="true">
  <proof prover="3"><result status="valid" time="0.08" steps="19061"/></proof>
  </goal>
  <goal name="VC selection_sort.10" expl="loop invariant preservation" proved="true">
  <proof prover="3"><result status="valid" time="0.04" steps="12982"/></proof>
  </goal>
  <goal name="VC selection_sort.11" expl="loop invariant preservation" proved="true">
  <proof prover="3"><result status="valid" time="0.08" steps="18550"/></proof>
  </goal>
  <goal name="VC selection_sort.12" expl="precondition" proved="true">
  <proof prover="3"><result status="valid" time="0.08" steps="20543"/></proof>
  </goal>
  <goal name="VC selection_sort.13" expl="precondition" proved="true">
  <proof prover="3"><result status="valid" time="0.08" steps="20826"/></proof>
  </goal>
  <goal name="VC selection_sort.14" expl="loop invariant preservation" proved="true">
  <proof prover="0"><result status="valid" time="0.51" steps="1193457"/></proof>
  </goal>
  <goal name="VC selection_sort.15" expl="loop invariant preservation" proved="true">
  <proof prover="3"><result status="valid" time="0.04" steps="17626"/></proof>
  </goal>
  <goal name="VC selection_sort.16" expl="loop invariant preservation" proved="true">
  <proof prover="2"><result status="valid" time="2.31" steps="4091"/></proof>
  </goal>
  <goal name="VC selection_sort.17" expl="loop invariant preservation" proved="true">
  <proof prover="0"><result status="valid" time="0.06" steps="66110"/></proof>
  </goal>
  <goal name="VC selection_sort.18" expl="loop invariant preservation" proved="true">
  <proof prover="3"><result status="valid" time="0.04" steps="16549"/></proof>
  </goal>
  <goal name="VC selection_sort.19" expl="loop invariant preservation" proved="true">
  <proof prover="3"><result status="valid" time="0.06" steps="19454"/></proof>
  </goal>
  <goal name="VC selection_sort.20" expl="out of loop bounds" proved="true">
  <proof prover="3"><result status="valid" time="0.04" steps="17536"/></proof>
  </goal>
  <goal name="VC selection_sort.21" expl="postcondition" proved="true">
  <proof prover="3"><result status="valid" time="0.06" steps="19715"/></proof>
  </goal>
  <goal name="VC selection_sort.22" expl="postcondition" proved="true">
  <proof prover="3"><result status="valid" time="0.06" steps="18731"/></proof>
  </goal>
 </transf>
 </goal>
 <goal name="VC test1" expl="VC for test1" proved="true">
 <proof prover="1"><result status="valid" time="0.00" steps="13"/></proof>
 </goal>
 <goal name="VC test2" expl="VC for test2" proved="true">
 <proof prover="1"><result status="valid" time="0.01" steps="40"/></proof>
 </goal>
 <goal name="VC bench" expl="VC for bench" proved="true">
 <proof prover="1"><result status="valid" time="0.01" steps="28"/></proof>
 </goal>
</theory>
</file>
</why3session>
